gamify/__init__.py
gamify/gamify.py
gamify-0.0.1.dist-info/METADATA
gamify-0.0.1.dist-info/WHEEL
gamify-0.0.1.dist-info/top_level.txt
gamify-0.0.1.dist-info/RECORD
