Metadata-Version: 2.1
Name: gamify
Version: 0.0.1
Summary: Talos Hyperparameter Tuning for Keras
Home-page: http://autonom.io
Author: Mikko Kotila
Author-email: mailme@mikkokotila.com
Maintainer: Mikko Kotila
Maintainer-email: mailme@mikkokotila.com
License: MIT
Download-URL: https://github.com/autonomio/gamify/
Platform: UNKNOWN
Classifier: Intended Audience :: Science/Research
Classifier: Programming Language :: Python :: 2.7
Classifier: Programming Language :: Python :: 3.5
Classifier: Programming Language :: Python :: 3.6
Classifier: License :: OSI Approved :: MIT License
Classifier: Topic :: Scientific/Engineering :: Human Machine Interfaces
Classifier: Topic :: Scientific/Engineering :: Artificial Intelligence
Classifier: Topic :: Scientific/Engineering :: Mathematics
Classifier: Operating System :: POSIX
Classifier: Operating System :: Unix
Classifier: Operating System :: MacOS
Classifier: Operating System :: Microsoft :: Windows :: Windows 10
Requires-Dist: flask
